ecgdetectors.py
ecgtemplates.py
hrv.py
py_ecg_detectors-1.3.5.dist-info/LICENSE
py_ecg_detectors-1.3.5.dist-info/METADATA
py_ecg_detectors-1.3.5.dist-info/WHEEL
py_ecg_detectors-1.3.5.dist-info/top_level.txt
py_ecg_detectors-1.3.5.dist-info/RECORD
