Metadata-Version: 2.1
Name: py-ecg-detectors
Version: 1.3.5
Summary: Eight ECG heartbeat detection algorithms and heartrate variability analysis
Home-page: https://github.com/berndporr/py-ecg-qrs-detectors
Author: Luis Howell, Bernd Porr
Author-email: luisbhowell@gmail.com, bernd.porr@glasgow.ac.uk
License: GPL 3.0
Platform: UNKNOWN
Classifier: Intended Audience :: Developers
Classifier: Operating System :: OS Independent
Classifier: Programming Language :: Python :: 3
License-File: LICENSE
